robster/__init__.py
robster/model/LinearModel.py
robster/model/__init__.py
robster/model/linear_model.py
robster/perceptron/SingleLayerPerceptron.py
robster/perceptron/__init__.py
robster/util/__init__.py
robster/util/checker.py
robster-0.2.5.dist-info/METADATA
robster-0.2.5.dist-info/WHEEL
robster-0.2.5.dist-info/top_level.txt
robster-0.2.5.dist-info/RECORD
