Metadata-Version: 2.1
Name: robster
Version: 0.2.5
Summary: UNKNOWN
Home-page: https://github.com/Ho-Jun-Moon/robster
Author: papamoon0113
Author-email: papamoon0113@pusan.ac.kr
License: UNKNOWN
Platform: UNKNOWN
Classifier: Programming Language :: Python :: 3
Classifier: License :: OSI Approved :: MIT License
Classifier: Operating System :: OS Independent
Requires-Python: >=3.6
Requires-Dist: numpy
